{"createpdf":["pdf'yedönüştür","pdfoluştur"],"word-to-pdf":["docxtopdfçevirme","worddosyasınıpdfçevirme","dönüştürün","wordpdfdönüştürme","word'denpdf'ye","wordpdfyeçevirme","pdfkelimesi","wordücretsizkullan","docxpdfçevirme","worddenpdfyedönüştürme","wordenpdfyedönüştür","wordüpdf","wordadobeçevirme","kelimeyipdf'yedönüştür","cpnvertwordtopdf","wordpdfyecevirme","wordbelgesipdfdönüştürme","worddosyasınıpdfyeçevirme","worddenpdfdönüştürme","çevrimiçiword","wordpdfcevirme","docpdfçevirme","wordbelgesi","onlinewordkullan","docdosyasıpdfçevirme","word'üpdfçevirme","wordpdfçevirmeadobe","word'üpdfyedönüştür","onlinewordbelgesioluşturma","wordpdfyedönüştürme","wordotpdf","pdfwordçevirmeadobe","wordonlinekullan","worddosyasınıpdfyedönüştür","worldpdfcevir","wordonlinegiriş","worddosyasınıpdfyeçevirmek","üilekelime","wordenpdfyeçevirme","worddosyasınıpdfdönüştürme","docpdfdönüştürme","worldpdfçevirme","worldüpdfçevirme","adobedosyasınıpdfyeçevirme","wordupdfçevirme","worddenpdfyeçevirme","wordpdfçevirme","wordpdfdönüştürmek","word'denpdf'yedönüştürme","worddenpdfye","word'üpdfye","word'üpdfyeçevirmeonline","docxdosyasınıpdfçevirme","docxpdfdönüştürme","wordupdfyedönüştürme","wordücretsiz","wordpdfdonusturme","worddosyasını","wordupdfyeçevir","wordtodf","word'üpdfyedönüştürmek","wordpdfyedönüştür","wordbelgesipdfçevirme","wordsayfasınıpdfyedönüştürme","worddosyasınıpdfformatınaçevirme","word'üpdfyeçevirme","worddosyasıpdf","wordüpdfyeçevirme","jpgyidocaçevirme","wordtopdfçevirme","worddosyasınıpdf","word'üpdfdönüştürme","worddosyasınıpdfyeçevirmeadobe","wordupdfyeçevirme","wordtopdfücretsiz","wordinpf","onlinewordbelgesi","docwordenpdf","docdosyasınıjpgyeçevirme","worddosyasındanpdfyeçevirme","wordropdfconverter","worddosyasıpdfçevirme","ücretsizmicrosoftword","word'üpdfyedönüştürme","word'üpdf"],"excel-to-pdf":["excelipdfyeçevirme","xlsdosyası","dönüştürün","exceli","xlsxdosyası","pdf'yeexcel","exceldosyası","xlsxdosyasınıxlsyeçevirme","excelpdfdönüştürme","exeli","çevrimiçiexcel","excelgirişyap","exceldosyasi","ileriexcelpdf","excel'ipdf'yedönüştür","ücretsizexceldosyaları","ücretsizexcel","xlstopdfdönüştürme","microsoftgirişyap"],"compress-pdf":["minifypdfonline","pdfminify","sikistir","pdfsıkıştırmaonline","dosyasıkıştırmaonline","pdfsıkıştırmaücretsiz","onlinepptküçültme","pdfboyutunuküçült","pdfsıkıştır","minifypdf","pptdosyaboyutuküçültme","wordsıkıştırma","ücretsizpdfsıkıştırma","pdfdosyasıkıştırmaonline","adobepdfsıkıştırma","onlinepdfsıkıştırma"],"ppt-to-pdf":["pdftopptücretsiz","pptxpdfdönüştürme","pptxdenpdf","powerpointgiriş","slaytdosyasınıpdfyeçevirme","pptformatınıpdfçevirme","pptxwordeçevirme","pptdopdf","dönüştür","pptpdfçevirmeücretsiz","pptyipdfçevirme","worddosyasınıpptyeçevirme","pptyopdf","powerpointtenpdfeçevirme","powerpointtopdfconverter","powerpointonli","pptopdf","pptdosyasınıpdfyedönüştürme","pptxpdfdönüştürücü","pptyipdfyedönüştürme","powerpointücretlimi","hazırpowerpoint","ppt'yipdf'yedönüştür","powerpointücretsiz","powerpointpdfdönüştürme","powerpointpdfçevir","pptxipdfyedönüştürme","pptgiriş","pptyijpgyeçevirme","powerpointçevrimiçi","pptwordeçevirme","pptpdfçevirme","pptyipdfyeçevirme","pptdenpdf","ppt'denpdf'ye","pptpdfdönüştürme","powerpointpdfçevirme","slayttopdf","powerpointonlinekullan"],"jpg-to-pdf":["jpgpdfdönüştürme","dönüştürün","jpgdönüştür","jpg'denpdf'ye","jpgpnggifdönüştürücü","jpgtopdfio","jpgtopdfçevirme","bmpdosyasınıpdfyeçevirme","jpg'yipdf'yedönüştür","bmpyijpgyeçevirme","pngyipdfyedönüştürme","worddosyasınıjpgyeçevirme","jpgbmpçevirme","jpegpdfdönüştürme","jpgyipptyeçevirme","jpgpdfyedönüştürme","bmpdosyasınıpdfçevirme","bmppdfçevirme","pdfgifdönüştürme","pngdosyasınıjpgyeçevirme","jpgdosyasınıpdfdönüştürme","bmpyipdfyeçevirme"]}